tesppypi/__init__.py
tesppypi/hello.py
tesppypi-1.0.2.dist-info/METADATA
tesppypi-1.0.2.dist-info/WHEEL
tesppypi-1.0.2.dist-info/top_level.txt
tesppypi-1.0.2.dist-info/RECORD
