Metadata-Version: 2.1
Name: tesppypi
Version: 1.0.2
Summary: A package working with financial data
Home-page: https://github.com/misrori/goldhand
Author: Mihaly
Author-email: ormraat.pte@gmail.com
License: MIT
